mumbojumbo/__init__.py
mumbojumbo/models/__init__.py
mumbojumbo/models/project_template.py
mumbojumbo/models/template_variable.py
mumbojumbo/scripts/__init__.py
mumbojumbo/scripts/apply_template.py
mumbojumbo/template_loader.py
mumbojumbo/template_renderer.py
mumbojumbo-0.1.0.dist-info/LICENSE
mumbojumbo-0.1.0.dist-info/METADATA
mumbojumbo-0.1.0.dist-info/WHEEL
mumbojumbo-0.1.0.dist-info/entry_points.txt
mumbojumbo-0.1.0.dist-info/RECORD
