Metadata-Version: 2.1
Name: mumbojumbo
Version: 0.1.0
Summary: A template-based project generator that takes care of all the mumbo-jumbo.
Home-page: https://github.com/phohenecker/mumbo-jumbo
License: BSD-3-Clause
Author: Patrick Hohenecker
Author-email: patrick.hohenecker@gmx.at
Requires-Python: >=3.12,<4.0
Classifier: License :: OSI Approved :: BSD License
Classifier: Programming Language :: Python :: 3
Classifier: Programming Language :: Python :: 3.12
Requires-Dist: jinja2 (>=3.1.3,<4.0.0)
Requires-Dist: jsonschema (>=4.21.1,<5.0.0)
Requires-Dist: tabulate (>=0.9.0,<0.10.0)
Project-URL: Repository, https://github.com/phohenecker/mumbo-jumbo
